mailsend.py
mailsend-2.0.0.dist-info/licenses/LICENSE
mailsend-2.0.0.dist-info/METADATA
mailsend-2.0.0.dist-info/WHEEL
mailsend-2.0.0.dist-info/top_level.txt
mailsend-2.0.0.dist-info/RECORD
