Metadata-Version: 2.4
Name: mailsend
Version: 2.0.0
Summary: Fork of tinysmtp with bug fixes and Python 3 compatibility
Author-email: Oliver Cope <oliver@redgecko.org>, Rick Harris <rconradharris@gmail.com>
License: BSD-3-Clause
Project-URL: homepage, https://hg.sr.ht/~olly/mailsend
Keywords: tinymtp,flask-mail,mail,smtp
Classifier: Environment :: Web Environment
Classifier: Intended Audience :: Developers
Classifier: Operating System :: OS Independent
Classifier: Programming Language :: Python
Classifier: Topic :: Internet :: WWW/HTTP :: Dynamic Content
Classifier: Topic :: Software Development :: Libraries :: Python Modules
Requires-Python: >=3.9
License-File: LICENSE
Requires-Dist: envparse>=0.2
Dynamic: license-file
